bytedinkfish/__init__.py
bytedinkfish-0.0.1.dist-info/METADATA
bytedinkfish-0.0.1.dist-info/WHEEL
bytedinkfish-0.0.1.dist-info/top_level.txt
bytedinkfish-0.0.1.dist-info/RECORD
